{"fonts/Antipasto-Pro-Regular-trial.ttf":["fonts/Antipasto-Pro-Regular-trial.ttf"],"fonts/Emily Olivia.otf":["fonts/Emily Olivia.otf"],"fonts/Florence-Regular.otf":["fonts/Florence-Regular.otf"],"fonts/Handineat.otf":["fonts/Handineat.otf"],"fonts/Hello Avocado.otf":["fonts/Hello Avocado.otf"],"fonts/Letters for Learners.ttf":["fonts/Letters for Learners.ttf"],"fonts/Mochi Cakes_DEMO.ttf":["fonts/Mochi Cakes_DEMO.ttf"],"fonts/Neonblitz.ttf":["fonts/Neonblitz.ttf"],"fonts/Nirmala Trial.otf":["fonts/Nirmala Trial.otf"],"fonts/Pacifico.ttf":["fonts/Pacifico.ttf"],"fonts/Papernotes.ttf":["fonts/Papernotes.ttf"],"fonts/Pistara.otf":["fonts/Pistara.otf"],"fonts/Power Smash.ttf":["fonts/Power Smash.ttf"],"fonts/Quick Cat.otf":["fonts/Quick Cat.otf"],"fonts/Quicksand_Bold.otf":["fonts/Quicksand_Bold.otf"],"fonts/Quicksand_Bold_Oblique.otf":["fonts/Quicksand_Bold_Oblique.otf"],"fonts/Quicksand_Book.otf":["fonts/Quicksand_Book.otf"],"fonts/Quicksand_Book_Oblique.otf":["fonts/Quicksand_Book_Oblique.otf"],"fonts/Quicksand_Dash.otf":["fonts/Quicksand_Dash.otf"],"fonts/Quicksand_Light.otf":["fonts/Quicksand_Light.otf"],"fonts/Quicksand_Light_Oblique.otf":["fonts/Quicksand_Light_Oblique.otf"],"fonts/Retrolight.otf":["fonts/Retrolight.otf"],"fonts/Robaga Rounded Regular.otf":["fonts/Robaga Rounded Regular.otf"],"fonts/Sirukota.ttf":["fonts/Sirukota.ttf"],"fonts/Sunny Spells Basic.ttf":["fonts/Sunny Spells Basic.ttf"],"fonts/Vintage Avalanche Black.otf":["fonts/Vintage Avalanche Black.otf"],"fonts/Vintage Avalanche.otf":["fonts/Vintage Avalanche.otf"],"fonts/Vintage.ttf":["fonts/Vintage.ttf"],"fonts/Western Retro.ttf":["fonts/Western Retro.ttf"],"fonts/manbow lines.otf":["fonts/manbow lines.otf"],"fonts/street cred.otf":["fonts/street cred.otf"],"images/bgqr.png":["images/bgqr.png"],"images/ic_launcher.png":["images/ic_launcher.png"],"images/insignias/anauyaca.png":["images/insignias/anauyaca.png"],"images/insignias/coati.png":["images/insignias/coati.png"],"images/insignias/jaguar.png":["images/insignias/jaguar.png"],"images/insignias/mantarraya.png":["images/insignias/mantarraya.png"],"images/insignias/tiburon.png":["images/insignias/tiburon.png"],"images/insignias/tortuga.png":["images/insignias/tortuga.png"],"images/insignias/tucan.png":["images/insignias/tucan.png"],"images/logo.jpeg":["images/logo.jpeg"],"images/no_image.png":["images/no_image.png"],"images/no_image2.png":["images/no_image2.png"],"images/premios/bici.png":["images/premios/bici.png"],"images/premios/buceo.png":["images/premios/buceo.png"],"images/premios/catamaran(1).png":["images/premios/catamaran(1).png"],"images/premios/chichenitza.png":["images/premios/chichenitza.png"],"images/premios/cirqueDuSoleil.png":["images/premios/cirqueDuSoleil.png"],"images/premios/departamento.png":["images/premios/departamento.png"],"images/premios/donativo.png":["images/premios/donativo.png"],"images/premios/europa.png":["images/premios/europa.png"],"images/premios/fiestaCasa.png":["images/premios/fiestaCasa.png"],"images/premios/huichol.png":["images/premios/huichol.png"],"images/premios/ikal.png":["images/premios/ikal.png"],"images/premios/jeep.png":["images/premios/jeep.png"],"images/premios/motoneta(1).png":["images/premios/motoneta(1).png"],"images/premios/nintendo.png":["images/premios/nintendo.png"],"images/premios/omakase(1).png":["images/premios/omakase(1).png"],"images/premios/paracaidas.png":["images/premios/paracaidas.png"],"images/premios/regalo_2.png":["images/premios/regalo_2.png"],"images/premios/regalo_3.png":["images/premios/regalo_3.png"],"images/premios/regalo_4.png":["images/premios/regalo_4.png"],"images/premios/sanMiguel.png":["images/premios/sanMiguel.png"],"images/premios/vespa.png":["images/premios/vespa.png"],"packages/cupertino_icons/assets/CupertinoIcons.ttf":["packages/cupertino_icons/assets/CupertinoIcons.ttf"],"packages/font_awesome_flutter/lib/fonts/fa-brands-400.ttf":["packages/font_awesome_flutter/lib/fonts/fa-brands-400.ttf"],"packages/font_awesome_flutter/lib/fonts/fa-regular-400.ttf":["packages/font_awesome_flutter/lib/fonts/fa-regular-400.ttf"],"packages/font_awesome_flutter/lib/fonts/fa-solid-900.ttf":["packages/font_awesome_flutter/lib/fonts/fa-solid-900.ttf"],"packages/iconsax_flutter/fonts/FlutterIconsax.ttf":["packages/iconsax_flutter/fonts/FlutterIconsax.ttf"]}